CHANGELOG.md
lightweightdebugmessages/LightweightDebugMessages.py
lightweightdebugmessages/__init__.py
lightweightdebugmessages/unittests/__init__.py
lightweightdebugmessages/unittests/common.py
lightweightdebugmessages/unittests/test_LightweightDebugMessages.py
lightweightdebugmessages/version.py
lightweightdebugmessages-0.1.0.1.dist-info/LICENSE
lightweightdebugmessages-0.1.0.1.dist-info/METADATA
lightweightdebugmessages-0.1.0.1.dist-info/WHEEL
lightweightdebugmessages-0.1.0.1.dist-info/RECORD
